DiscordUtils/InviteTracker.py
DiscordUtils/Music.py
DiscordUtils/Pagination.py
DiscordUtils/__init__.py
DiscordUtils-1.3.2.dist-info/LICENSE.txt
DiscordUtils-1.3.2.dist-info/METADATA
DiscordUtils-1.3.2.dist-info/WHEEL
DiscordUtils-1.3.2.dist-info/top_level.txt
DiscordUtils-1.3.2.dist-info/RECORD
