Metadata-Version: 2.1
Name: DiscordUtils
Version: 1.3.2
Summary: DiscordUtils is a very useful library made to be used with discord.py
Home-page: https://www.github.com/toxicrecker/DiscordUtils
Author: toxicrecker
License: UNKNOWN
Platform: UNKNOWN
Classifier: Programming Language :: Python :: 3
Classifier: License :: OSI Approved :: MIT License
Classifier: Operating System :: OS Independent
Requires-Python: >= 3.6
Requires-Dist: discord.py
Provides-Extra: voice
Requires-Dist: discord.py[voice] ; extra == 'voice'
Requires-Dist: youtube-dl ; extra == 'voice'
